arithmetic_calc/Calculator.py
arithmetic_calc/__init__.py
arithmetic_calc-0.1.dist-info/LICENSE
arithmetic_calc-0.1.dist-info/WHEEL
arithmetic_calc-0.1.dist-info/METADATA
arithmetic_calc-0.1.dist-info/RECORD
