Metadata-Version: 2.1
Name: arithmetic_calc
Version: 0.1
Summary: Arithmetic Calculator
Author-email: Ibsa Abraham <ibsaabraham663@gmail.com>
Classifier: License :: OSI Approved :: MIT License
